{
  "$schema": "../gen/schemas/desktop-schema.json",
  "identifier": "default",
  "description": "Capability for the pet and settings windows",
  "windows": ["main", "settings"],
  "permissions": [
    "core:default",
    "opener:default",
    "dialog:default",
    "store:default",
    "core:window:allow-close",
    "core:window:allow-create",
    "core:window:allow-set-position",
    "core:window:allow-start-dragging",
    "core:window:allow-show",
    "core:window:allow-hide",
    "core:window:allow-set-focus",
    "core:window:allow-set-title",
    "core:window:allow-set-size",
    "core:event:default",
    "core:event:allow-listen",
    "core:event:allow-emit",
    "notification:default",
    "sql:default",
    "sql:allow-load",
    "sql:allow-execute",
    "sql:allow-select",
    "sql:allow-close"
  ]
}
